augments_mcp/__init__.py
augments_mcp/__main__.py
augments_mcp/main.py
augments_mcp/server.py
augments_mcp/server_improved.py
augments_mcp/server_never_fail.py
augments_mcp/web_server.py
augments_mcp/middleware/__init__.py
augments_mcp/middleware/abuse_detector.py
augments_mcp/middleware/cloudflare.py
augments_mcp/middleware/edge_cache.py
augments_mcp/middleware/request_coalescer.py
augments_mcp/middleware/smart_limiter.py
augments_mcp/models/__init__.py
augments_mcp/providers/__init__.py
augments_mcp/providers/base.py
augments_mcp/providers/github.py
augments_mcp/providers/website.py
augments_mcp/registry/__init__.py
augments_mcp/registry/cache.py
augments_mcp/registry/manager.py
augments_mcp/registry/models.py
augments_mcp/tools/__init__.py
augments_mcp/tools/context_enhancement.py
augments_mcp/tools/documentation.py
augments_mcp/tools/documentation_improved.py
augments_mcp/tools/documentation_never_fail.py
augments_mcp/tools/documentation_simple_fix.py
augments_mcp/tools/framework_discovery.py
augments_mcp/tools/updates.py
augments_mcp/utils/__init__.py
augments_mcp/utils/github_client.py
augments_mcp/utils/validation.py
augments_mcp_server-2.0.5.dist-info/licenses/LICENSE
augments_mcp_server-2.0.5.dist-info/METADATA
augments_mcp_server-2.0.5.dist-info/WHEEL
augments_mcp_server-2.0.5.dist-info/entry_points.txt
augments_mcp_server-2.0.5.dist-info/top_level.txt
augments_mcp_server-2.0.5.dist-info/RECORD
