Metadata-Version: 2.4
Name: augments-mcp-server
Version: 2.0.5
Summary: Augments MCP Server - A comprehensive framework documentation provider for Claude Code
Author: augmnt
License: MIT
Project-URL: Homepage, https://augments.dev
Project-URL: Repository, https://github.com/augmnt/augments-mcp-server
Project-URL: Issues, https://github.com/augmnt/augments-mcp-server/issues
Keywords: mcp,claude,documentation,framework,ai,development-tools
Classifier: Development Status :: 5 - Production/Stable
Classifier: Intended Audience :: Developers
Classifier: License :: OSI Approved :: MIT License
Classifier: Programming Language :: Python :: 3
Classifier: Programming Language :: Python :: 3.11
Classifier: Programming Language :: Python :: 3.12
Classifier: Topic :: Software Development :: Documentation
Classifier: Topic :: Software Development :: Libraries :: Python Modules
Requires-Python: >=3.11
License-File: LICENSE
Requires-Dist: fastmcp>=0.1.0
Requires-Dist: fastapi>=0.109.0
Requires-Dist: uvicorn[standard]>=0.27.0
Requires-Dist: gunicorn>=21.2.0
Requires-Dist: wsproto>=1.2.0
Requires-Dist: httpx[http2]>=0.25.0
Requires-Dist: aiofiles>=23.0.0
Requires-Dist: beautifulsoup4>=4.12.0
Requires-Dist: pydantic>=2.0.0
Requires-Dist: markdownify>=0.11.0
Requires-Dist: redis[hiredis]>=5.0.0
Requires-Dist: diskcache>=5.6.0
Requires-Dist: python-dotenv>=1.0.0
Requires-Dist: structlog>=24.0.0
Requires-Dist: rich>=13.0.0
Requires-Dist: click>=8.1.0
Requires-Dist: slowapi>=0.1.9
Requires-Dist: python-jose[cryptography]>=3.3.0
Requires-Dist: passlib[bcrypt]>=1.7.4
Requires-Dist: prometheus-client>=0.19.0
Requires-Dist: watchdog>=3.0.0
Dynamic: license-file
